Metadata-Version: 1.1
Name: coop-geo
Version: 0.2.0
Summary: GeoDjango fields and geo widgets for django-coop
Home-page: https://github.com/quinode/coop-geo/
Author: Etienne Loks
Author-email: etienne.loks@peacefrogs.net
License: BSD
Download-URL: https://github.com/quinode/coop-geo/tarball/master
Platform: UNKNOWN
Classifier: Development Status :: 4 - Beta
Classifier: Environment :: Web Environment
Classifier: Intended Audience :: Developers
Classifier: License :: OSI Approved :: BSD License
Classifier: Operating System :: OS Independent
Classifier: Programming Language :: Python
Classifier: Framework :: Django
Classifier: Natural Language :: English
Classifier: Natural Language :: French
Classifier: Topic :: Internet :: WWW/HTTP :: Dynamic Content
Classifier: Topic :: Internet :: WWW/HTTP :: WSGI :: Application
